MANIFEST.in
pip-requirements-min-django.txt
pip-requirements-test.txt
pip-requirements.txt
setup.py
django_sec/__init__.py
django_sec/admin.py
django_sec/apps.py
django_sec/constants.py
django_sec/forms.py
django_sec/models.py
django_sec/settings.py
django_sec/utils.py
django_sec/xbrl.py
django_sec/xbrl_fundamentals.py
django_sec.egg-info/PKG-INFO
django_sec.egg-info/SOURCES.txt
django_sec.egg-info/dependency_links.txt
django_sec.egg-info/not-zip-safe
django_sec.egg-info/requires.txt
django_sec.egg-info/top_level.txt
django_sec/management/__init__.py
django_sec/management/commands/__init__.py
django_sec/management/commands/sec_import_attrs.py
django_sec/management/commands/sec_import_index.py
django_sec/management/commands/sec_mark_units.py
django_sec/management/commands/sec_xbrl_to_csv.py
django_sec/migrations/0001_initial.py
django_sec/migrations/__init__.py
django_sec/south_migrations/0001_initial.py
django_sec/south_migrations/0002_auto__add_field_index__ticker.py
django_sec/south_migrations/0003_auto__add_index_index_company_date_filename.py
django_sec/south_migrations/0004_auto__chg_field_attributevalue_value.py
django_sec/south_migrations/0005_auto__add_field_company_min_date__add_field_company_max_date.py
django_sec/south_migrations/__init__.py
django_sec/tests/__init__.py
django_sec/tests/manage.py
django_sec/tests/models.py
django_sec/tests/settings.py
django_sec/tests/tests.py
django_sec/tests/urls.py
django_sec/tests/views.py
django_sec/tests/management/__init__.py
django_sec/tests/management/commands/__init__.py